.travis.yml
licence
readme.md
requirements-dev.txt
requirements.txt
setup.cfg
setup.py
tox.ini
pypirepo.egg-info/PKG-INFO
pypirepo.egg-info/SOURCES.txt
pypirepo.egg-info/dependency_links.txt
pypirepo.egg-info/not-zip-safe
pypirepo.egg-info/pbr.json
pypirepo.egg-info/requires.txt
pypirepo.egg-info/top_level.txt
src/readme.md
src/main/pypirepo/__init__.py
src/main/pypirepo/config.ini
src/main/pypirepo/config.py
src/main/pypirepo/login.py
src/main/pypirepo/manager.py
src/main/pypirepo/workflow.py
src/test/pypirepo_test/.pypirc
src/test/pypirepo_test/__init__.py
src/test/pypirepo_test/config_test.py
src/test/pypirepo_test/login_test.py
src/test/pypirepo_test/manager_test.py
src/test/pypirepo_test/workflow_test.py
src/verify/tool/__init__.py
tool/arkon.sh
tool/github_squash.sh
tool/provision_env.sh
tool/readme.md
tool/release_update.py